{
  "versionCode": 25,
  "versionName": "2.3.8",
  "apkUrl": "https://github.com/IISonGokuII/DjoudinisIPPlayer-releases/raw/main/DjoudinisIPPlayer-2.3.8.apk",
  "releaseNotes": "Djoudinis IP Player 2.3.8 (Build 25)\n\n• M3U: stabile IDs über tvg-id (Fallback URL-Hash), Legacy-IDs werden erkannt\n• Kids-Filter speichern Kategorie per remoteId+Typ+Playlist\n• Smarteres Name-Matching (FHD/HEVC/… werden ignoriert)\n\nUpdate über Einstellungen → System → Update prüfen.",
  "minVersionCode": 1,
  "sha256": "dc3b6ee8016e5988a467d50c12dadc5d20429bdaf9ba39c77221b880f1308b3b"
}
